LICENSE
MANIFEST.in
README.rst
setup.py
police_api/__init__.py
police_api/crime.py
police_api/exceptions.py
police_api/forces.py
police_api/neighbourhoods.py
police_api/resource.py
police_api/service.py
police_api/tests.py
police_api/utils.py
police_api/version.py
police_api_client.egg-info/PKG-INFO
police_api_client.egg-info/SOURCES.txt
police_api_client.egg-info/dependency_links.txt
police_api_client.egg-info/requires.txt
police_api_client.egg-info/top_level.txt