Metadata-Version: 1.1
Name: police-api-client
Version: 1.1.0
Summary: Python client library for the Police API
Home-page: https://github.com/rkhleics/police-api-client-python
Author: Rock Kitchen Harris
Author-email: UNKNOWN
License: MIT
Download-URL: https://github.com/rkhleics/police-api-client-python/downloads
Platform: UNKNOWN
